vidhub_control-0.0.3.dist-info/METADATA
vidhub_control-0.0.3.dist-info/RECORD
vidhub_control-0.0.3.dist-info/WHEEL
vidhub_control-0.0.3.dist-info/entry_points.txt
vidhub_control-0.0.3.dist-info/top_level.txt
vidhubcontrol/__init__.py
vidhubcontrol/aiotelnetlib.py
vidhubcontrol/config.py
vidhubcontrol/discovery.py
vidhubcontrol/runserver.py
vidhubcontrol/utils.py
vidhubcontrol/backends/__init__.py
vidhubcontrol/backends/base.py
vidhubcontrol/backends/dummy.py
vidhubcontrol/backends/telnet.py
vidhubcontrol/interfaces/__init__.py
vidhubcontrol/interfaces/osc/__init__.py
vidhubcontrol/interfaces/osc/interface.py
vidhubcontrol/interfaces/osc/node.py
vidhubcontrol/interfaces/osc/server.py
vidhubcontrol/kivyui/__init__.py
vidhubcontrol/kivyui/main.py
vidhubcontrol/kivyui/newdevice.py
vidhubcontrol/kivyui/smartview.py
vidhubcontrol/kivyui/utils.py
vidhubcontrol/kivyui/vidhubedit.py
vidhubcontrol/kivyui/vidhubpresetedit.py
vidhubcontrol/kivyui/vidhubview.py
vidhubcontrol/sofi_ui/__init__.py
vidhubcontrol/sofi_ui/main.py
