Metadata-Version: 2.1
Name: vidhub-control
Version: 0.0.3
Summary: Control Smart Videohub Devices
Home-page: https://github.com/nocarryr/vidhub-control
Author: Matthew Reid
Author-email: matt@nomadic-recording.com
License: UNKNOWN
Platform: any
Classifier: Development Status :: 3 - Alpha
Classifier: License :: OSI Approved :: GNU Lesser General Public License v3 (LGPLv3)
Classifier: Operating System :: OS Independent
Classifier: Programming Language :: Python
Classifier: Programming Language :: Python :: 3
Classifier: Programming Language :: Python :: 3.5
Classifier: Framework :: AsyncIO
Classifier: Intended Audience :: Developers
Classifier: Intended Audience :: End Users/Desktop
Classifier: Topic :: Multimedia
Classifier: Topic :: Multimedia :: Graphics
Classifier: Topic :: Multimedia :: Video
Requires-Python: >=3.5
Provides-Extra: kivy
Requires-Dist: python-dispatch (>=0.0.8)
Requires-Dist: json-object-factory
Requires-Dist: zeroconf
Requires-Dist: python-osc
Requires-Dist: pid
Provides-Extra: kivy
Requires-Dist: kivy (>=1.10.0); extra == 'kivy'
